gridvoting_jax/__init__.py
gridvoting_jax/datasets.py
gridvoting_jax/geometry.py
gridvoting_jax/py.typed
gridvoting_jax/symmetry.py
gridvoting_jax/benchmarks/__init__.py
gridvoting_jax/benchmarks/bjm_comparison.py
gridvoting_jax/core/__init__.py
gridvoting_jax/core/config.py
gridvoting_jax/core/constants.py
gridvoting_jax/models/__init__.py
gridvoting_jax/models/base.py
gridvoting_jax/models/budget.py
gridvoting_jax/models/budget_voting_draft.py
gridvoting_jax/models/spatial.py
gridvoting_jax/models/examples/__init__.py
gridvoting_jax/models/examples/bjm_budget.py
gridvoting_jax/models/examples/bjm_spatial.py
gridvoting_jax/models/examples/condorcet.py
gridvoting_jax/models/examples/plott_theorem.py
gridvoting_jax/models/examples/shapes/__init__.py
gridvoting_jax/models/examples/shapes/ring.py
gridvoting_jax/models/examples/shapes/triangle.py
gridvoting_jax/stochastic/__init__.py
gridvoting_jax/stochastic/lazy_q.py
gridvoting_jax/stochastic/lazy_stochastic.py
gridvoting_jax/stochastic/lazy_weighted_stochastic.py
gridvoting_jax/stochastic/markov.py
gridvoting_jax/stochastic/utils.py
gridvoting_jax-0.47.0.dist-info/licenses/LICENSE.md
gridvoting_jax-0.47.0.dist-info/METADATA
gridvoting_jax-0.47.0.dist-info/WHEEL
gridvoting_jax-0.47.0.dist-info/top_level.txt
gridvoting_jax-0.47.0.dist-info/RECORD
