Metadata-Version: 2.4
Name: gridvoting-jax
Version: 0.47.0
Summary: Spatial voting simulations on a grid with random challengers (with float32 JAX backend)
Home-page: https://github.com/drpaulbrewer/gridvoting-jax
Author: Paul Brewer
Author-email: drpaulbrewer@eaftc.com
License: MIT
Project-URL: Bug Tracker, https://github.com/drpaulbrewer/gridvoting-jax/issues
Project-URL: Original Project, https://github.com/drpaulbrewer/gridvoting
Classifier: Programming Language :: Python :: 3
Classifier: Programming Language :: Python :: 3.10
Classifier: Programming Language :: Python :: 3.11
Classifier: Programming Language :: Python :: 3.12
Classifier: Operating System :: POSIX :: Linux
Classifier: Operating System :: MacOS
Classifier: Operating System :: Microsoft :: Windows
Classifier: Development Status :: 3 - Alpha
Classifier: Environment :: GPU :: NVIDIA CUDA
Classifier: Environment :: GPU
Classifier: Intended Audience :: Science/Research
Classifier: Topic :: Scientific/Engineering :: Artificial Intelligence
Classifier: Topic :: Scientific/Engineering :: Mathematics
Requires-Python: >=3.10
License-File: LICENSE.md
Requires-Dist: numpy>=2.0.0
Requires-Dist: matplotlib>=3.8.0
Requires-Dist: jax>=0.4.20
Requires-Dist: chex>=0.1.0
Requires-Dist: scipy>=1.12.0
Provides-Extra: dev
Requires-Dist: pytest>=7.0.0; extra == "dev"
Requires-Dist: pytest-cov>=4.0.0; extra == "dev"
Dynamic: license-file
